sheller/__init__.py
sheller/main.py
sheller_ai-1.0.0.dist-info/licenses/LICENSE.txt
sheller_ai-1.0.0.dist-info/METADATA
sheller_ai-1.0.0.dist-info/WHEEL
sheller_ai-1.0.0.dist-info/entry_points.txt
sheller_ai-1.0.0.dist-info/top_level.txt
sheller_ai-1.0.0.dist-info/RECORD
