Metadata-Version: 2.4
Name: sheller-ai
Version: 1.0.0
Summary: AI-Powered Terminal Command Assistant - Natural Language to Commands
Author-email: Sheller Team <team@sheller.com>
License: MIT
Project-URL: Homepage, https://sheller.com
Project-URL: Documentation, https://docs.sheller.com
Project-URL: Repository, https://github.com/sheller/sheller
Project-URL: Issues, https://github.com/sheller/sheller/issues
Keywords: terminal,cli,ai,commands,shell,productivity
Classifier: Development Status :: 4 - Beta
Classifier: Intended Audience :: Developers
Classifier: Intended Audience :: End Users/Desktop
Classifier: License :: OSI Approved :: MIT License
Classifier: Operating System :: OS Independent
Classifier: Programming Language :: Python :: 3
Classifier: Programming Language :: Python :: 3.8
Classifier: Programming Language :: Python :: 3.9
Classifier: Programming Language :: Python :: 3.10
Classifier: Programming Language :: Python :: 3.11
Classifier: Programming Language :: Python :: 3.12
Classifier: Topic :: System :: Shells
Classifier: Topic :: System :: System Shells
Classifier: Topic :: Utilities
Requires-Python: >=3.8
License-File: LICENSE.txt
Requires-Dist: pydantic>=2.0.0
Requires-Dist: python-dotenv>=1.0.0
Requires-Dist: google-generativeai>=0.3.0
Dynamic: license-file
